statham/__init__.py
statham/__main__.py
statham/py.typed
statham/titles.py
statham/schema/__init__.py
statham/schema/constants.py
statham/schema/exceptions.py
statham/schema/helpers.py
statham/schema/parser.py
statham/schema/property.py
statham/schema/elements/__init__.py
statham/schema/elements/array.py
statham/schema/elements/base.py
statham/schema/elements/boolean.py
statham/schema/elements/composition.py
statham/schema/elements/items.py
statham/schema/elements/meta.py
statham/schema/elements/null.py
statham/schema/elements/numeric.py
statham/schema/elements/object.py
statham/schema/elements/properties.py
statham/schema/elements/string.py
statham/schema/validation/__init__.py
statham/schema/validation/array.py
statham/schema/validation/base.py
statham/schema/validation/format.py
statham/schema/validation/numeric.py
statham/schema/validation/object.py
statham/schema/validation/string.py
statham/serializers/__init__.py
statham/serializers/json.py
statham/serializers/orderer.py
statham/serializers/python.py
statham_schema-0.15.1.dist-info/LICENSE.txt
statham_schema-0.15.1.dist-info/METADATA
statham_schema-0.15.1.dist-info/WHEEL
statham_schema-0.15.1.dist-info/entry_points.txt
statham_schema-0.15.1.dist-info/top_level.txt
statham_schema-0.15.1.dist-info/RECORD
