Metadata-Version: 2.1
Name: statham-schema
Version: 0.15.1
Summary: Tools for generating Python models from JSON Schema documents.
Home-page: https://github.com/jacksmith15/statham-schema
Author: Jack Smith
License: MIT
Platform: UNKNOWN
Classifier: Development Status :: 3 - Alpha
Classifier: Intended Audience :: Developers
Classifier: Programming Language :: Python :: 3.6
License-File: LICENSE.txt
Requires-Dist: PyYAML (~=6.0)
Requires-Dist: python-dateutil (~=2.8)
Requires-Dist: jsonpointer (~=2.0)
Requires-Dist: json-ref-dict (<0.8.0,>=0.6.2)
Requires-Dist: typing-extensions (<5.0.0,>=3.7.0)
